{
  "games": {
    "Chrono Trigger": {
      "game": "Chrono Trigger",
      "platforms": [
        "SNES",
        "PS1",
        "DS",
        "MSU1"
      ],
      "release_year": 1995,
      "developer": "Square",
      "characters": [
        {
          "id": 0,
          "name": "Crono",
          "hp": 100,
          "mp": 20,
          "str": 10,
          "speed": 10,
          "type": "swordsman"
        },
        {
          "id": 1,
          "name": "Marle",
          "hp": 80,
          "mp": 35,
          "str": 5,
          "speed": 12,
          "type": "healer"
        },
        {
          "id": 2,
          "name": "Lucca",
          "hp": 75,
          "mp": 40,
          "str": 6,
          "speed": 8,
          "type": "mage"
        },
        {
          "id": 3,
          "name": "Frog",
          "hp": 90,
          "mp": 25,
          "str": 12,
          "speed": 9,
          "type": "swordsman"
        },
        {
          "id": 4,
          "name": "Robo",
          "hp": 120,
          "mp": 15,
          "str": 15,
          "speed": 5,
          "type": "robot"
        },
        {
          "id": 5,
          "name": "Ayla",
          "hp": 150,
          "mp": 0,
          "str": 20,
          "speed": 15,
          "type": "fighter"
        },
        {
          "id": 6,
          "name": "Magus",
          "hp": 85,
          "mp": 50,
          "str": 8,
          "speed": 14,
          "type": "mage"
        }
      ],
      "weapons": [
        {
          "id": 0,
          "name": "cLaw"
        },
        {
          "id": 1,
          "name": "Lode Sword"
        },
        {
          "id": 2,
          "name": "Red Katana"
        },
        {
          "id": 3,
          "name": "Aeon Blade"
        },
        {
          "id": 4,
          "name": "AlloyBlade"
        },
        {
          "id": 5,
          "name": "Star Sword"
        },
        {
          "id": 6,
          "name": "VedicBlade"
        },
        {
          "id": 7,
          "name": "Kali Blade"
        },
        {
          "id": 8,
          "name": "Bolt Sword"
        },
        {
          "id": 9,
          "name": "Bronze Bow"
        },
        {
          "id": 10,
          "name": "Lode Bow"
        },
        {
          "id": 11,
          "name": "Robin Bow"
        },
        {
          "id": 12,
          "name": "Sage Bow"
        },
        {
          "id": 13,
          "name": "Dream Bow"
        },
        {
          "id": 14,
          "name": "Air Gun"
        },
        {
          "id": 15,
          "name": "Dart Gun"
        },
        {
          "id": 16,
          "name": "Auto Gun"
        },
        {
          "id": 17,
          "name": "Plasma Gun"
        },
        {
          "id": 18,
          "name": "Ruby Gun"
        },
        {
          "id": 19,
          "name": "Dream Gun"
        },
        {
          "id": 20,
          "name": "Hammer Arm"
        },
        {
          "id": 21,
          "name": "FlashBlade"
        },
        {
          "id": 22,
          "name": "Rune Blade"
        },
        {
          "id": 23,
          "name": "BraveSword"
        },
        {
          "id": 24,
          "name": "Bent Sword"
        },
        {
          "id": 25,
          "name": "Rainbow"
        },
        {
          "id": 26,
          "name": "Flare     RocketPunchCure Beam  Laser Spin Robo TackleHeal Beam  Uzzi Punch Area Bomb  Shock      Slurp      Slurp Cut"
        },
        {
          "id": 27,
          "name": "Ruby Gun"
        },
        {
          "id": 28,
          "name": "got a Ruby Gun"
        },
        {
          "id": 29,
          "name": "m Gun"
        }
      ],
      "armor": [
        {
          "id": 0,
          "name": "MaidenSuit"
        },
        {
          "id": 1,
          "name": "Titan Vest"
        },
        {
          "id": 2,
          "name": "Ruby Vest"
        },
        {
          "id": 3,
          "name": "Mist Robe"
        },
        {
          "id": 4,
          "name": "Lumin Robe"
        },
        {
          "id": 5,
          "name": "Lode Vest"
        },
        {
          "id": 6,
          "name": "Aeon Suit"
        },
        {
          "id": 7,
          "name": "Nova Armor"
        },
        {
          "id": 8,
          "name": "Moon Armor"
        },
        {
          "id": 9,
          "name": "Ruby Armor"
        },
        {
          "id": 10,
          "name": "RavenArmor"
        },
        {
          "id": 11,
          "name": "White Vest"
        },
        {
          "id": 12,
          "name": "Black Vest"
        },
        {
          "id": 13,
          "name": "Blue Vest"
        },
        {
          "id": 14,
          "name": "Red Vest"
        },
        {
          "id": 15,
          "name": "Taban Vest"
        },
        {
          "id": 16,
          "name": "Taban Suit"
        },
        {
          "id": 17,
          "name": "Flea Vest"
        },
        {
          "id": 18,
          "name": "Haste"
        },
        {
          "id": 19,
          "name": "Bike Ra"
        }
      ],
      "accessories": [
        {
          "name": "Power Glove",
          "effect": "STR+10"
        },
        {
          "name": "Hero's Medal",
          "effect": "STR+5, DEF+5"
        },
        {
          "name": "Powersquare",
          "effect": "STR+15"
        },
        {
          "name": "Silver Crown",
          "effect": "MP+20"
        },
        {
          "name": "Gold Crown",
          "effect": "MP+30"
        },
        {
          "name": "Ruby Crown",
          "effect": "MP+50"
        },
        {
          "name": "Earrings",
          "effect": "MP recovery"
        },
        {
          "name": "Rubin Band",
          "effect": "Evasion+20"
        },
        {
          "name": "Gold Gloves",
          "effect": "Counter"
        },
        {
          "name": "Siren's Kisses",
          "effect": "Protect"
        }
      ],
      "items": [
        {
          "id": 0,
          "name": "Masamune",
          "type": "key",
          "effect": "Legendary sword"
        },
        {
          "id": 1,
          "name": "Potion",
          "type": "item",
          "effect": "HP+50",
          "price": 10
        },
        {
          "id": 2,
          "name": "Ether",
          "type": "item",
          "effect": "MP+10",
          "price": 20
        },
        {
          "id": 3,
          "name": "Elixir",
          "type": "item",
          "effect": "Full restore",
          "price": 100
        },
        {
          "id": 4,
          "name": "Antidote",
          "type": "item",
          "effect": "Cure poison",
          "price": 5
        },
        {
          "id": 5,
          "name": "Tonic",
          "type": "item",
          "effect": "HP+30",
          "price": 5
        },
        {
          "id": 6,
          "name": "Smidt",
          "type": "item",
          "effect": "MP+5",
          "price": 10
        },
        {
          "id": 7,
          "name": "Power Drop",
          "type": "item",
          "effect": "STR+2",
          "price": 30
        },
        {
          "id": 8,
          "name": "Speed Drop",
          "type": "item",
          "effect": "SPD+2",
          "price": 30
        },
        {
          "id": 9,
          "name": "Magic Drop",
          "type": "item",
          "effect": "MP+5",
          "price": 30
        },
        {
          "id": 10,
          "name": "Tent",
          "type": "item",
          "effect": "Full heal party",
          "price": 150
        },
        {
          "id": 11,
          "name": "War Gear",
          "type": "item",
          "effect": "All stats up",
          "price": 200
        },
        {
          "id": 12,
          "name": "Prism",
          "type": "key",
          "effect": "Unlock seal"
        },
        {
          "id": 13,
          "name": "Gate Key",
          "type": "key",
          "effect": "Open sealed door"
        },
        {
          "id": 14,
          "name": "Bent Sword",
          "type": "key",
          "effect": "Frog's quest"
        },
        {
          "id": 15,
          "name": "Moon Stone",
          "type": "key",
          "effect": "Open Moon Bridge"
        },
        {
          "id": 16,
          "name": "Sun Stone",
          "type": "key",
          "effect": "Activate Sun Palace"
        },
        {
          "id": 17,
          "name": "Ruby Knife",
          "type": "key",
          "effect": "Ayla's quest"
        },
        {
          "id": 18,
          "name": "Clone",
          "type": "key",
          "effect": "Lucca's quest"
        },
        {
          "id": 19,
          "name": " Seymour's Key",
          "type": "key",
          "effect": "Open dungeon"
        }
      ],
      "enemies": [
        {
          "id": 0,
          "name": "Masa",
          "hp": 10,
          "exp": 1,
          "type": "enemy"
        },
        {
          "id": 1,
          "name": "Gnash",
          "hp": 15,
          "exp": 2,
          "type": "enemy"
        },
        {
          "id": 2,
          "name": "Rat",
          "hp": 20,
          "exp": 3,
          "type": "enemy"
        },
        {
          "id": 3,
          "name": "Flight",
          "hp": 30,
          "exp": 4,
          "type": "enemy"
        },
        {
          "id": 4,
          "name": "Jagger",
          "hp": 40,
          "exp": 5,
          "type": "enemy"
        },
        {
          "id": 5,
          "name": "Saucier",
          "hp": 35,
          "exp": 5,
          "type": "enemy"
        },
        {
          "id": 6,
          "name": "Cybot",
          "hp": 50,
          "exp": 8,
          "type": "enemy"
        },
        {
          "id": 7,
          "name": "Hawk",
          "hp": 45,
          "exp": 6,
          "type": "enemy"
        },
        {
          "id": 8,
          "name": "Riders",
          "hp": 80,
          "exp": 12,
          "type": "enemy"
        },
        {
          "id": 9,
          "name": "Leader",
          "hp": 100,
          "exp": 15,
          "type": "enemy"
        },
        {
          "id": 10,
          "name": "Gurguante",
          "hp": 120,
          "exp": 20,
          "type": "enemy"
        },
        {
          "id": 11,
          "name": "Vaper",
          "hp": 60,
          "exp": 10,
          "type": "enemy"
        },
        {
          "id": 12,
          "name": "Lapidon",
          "hp": 180,
          "exp": 30,
          "type": "enemy"
        },
        {
          "id": 13,
          "name": "Mystery",
          "hp": 250,
          "exp": 50,
          "type": "enemy"
        },
        {
          "id": 14,
          "name": "Gargoyle",
          "hp": 200,
          "exp": 40,
          "type": "enemy"
        },
        {
          "id": 15,
          "name": "Rage",
          "hp": 150,
          "exp": 25,
          "type": "enemy"
        },
        {
          "id": 16,
          "name": "Retinite",
          "hp": 280,
          "exp": 60,
          "type": "enemy"
        },
        {
          "id": 17,
          "name": "Hexapod",
          "hp": 200,
          "exp": 35,
          "type": "enemy"
        },
        {
          "id": 18,
          "name": "Marty",
          "hp": 180,
          "exp": 30,
          "type": "enemy"
        },
        {
          "id": 19,
          "name": "Necromancer",
          "hp": 300,
          "exp": 80,
          "type": "enemy"
        },
        {
          "id": 20,
          "name": "Dragon",
          "hp": 500,
          "exp": 100,
          "type": "boss"
        },
        {
          "id": 21,
          "name": "Mud Imp",
          "hp": 400,
          "exp": 80,
          "type": "boss"
        },
        {
          "id": 22,
          "name": "Yeti",
          "hp": 450,
          "exp": 90,
          "type": "boss"
        },
        {
          "id": 23,
          "name": "Golem",
          "hp": 600,
          "exp": 120,
          "type": "boss"
        },
        {
          "id": 24,
          "name": "Nizbel",
          "hp": 550,
          "exp": 100,
          "type": "boss"
        },
        {
          "id": 25,
          "name": "Nizbel II",
          "hp": 800,
          "exp": 200,
          "type": "boss"
        },
        {
          "id": 26,
          "name": "Magus",
          "hp": 1000,
          "exp": 0,
          "type": "boss"
        },
        {
          "id": 27,
          "name": "Lavos Spawn",
          "hp": 2000,
          "exp": 500,
          "type": "boss"
        },
        {
          "id": 28,
          "name": "Lavos",
          "hp": 12000,
          "exp": 0,
          "type": "final_boss"
        },
        {
          "id": 29,
          "name": "Scouter",
          "hp": 100,
          "exp": 15,
          "type": "enemy"
        },
        {
          "id": 30,
          "name": "Repair",
          "hp": 120,
          "exp": 18,
          "type": "enemy"
        },
        {
          "id": 31,
          "name": "Jinn",
          "hp": 150,
          "exp": 25,
          "type": "enemy"
        },
        {
          "id": 32,
          "name": "Boneman",
          "hp": 200,
          "exp": 35,
          "type": "enemy"
        },
        {
          "id": 33,
          "name": "Shadow",
          "hp": 80,
          "exp": 12,
          "type": "enemy"
        },
        {
          "id": 34,
          "name": "Hollow",
          "hp": 100,
          "exp": 15,
          "type": "enemy"
        },
        {
          "id": 35,
          "name": "Brawler",
          "hp": 180,
          "exp": 30,
          "type": "enemy"
        },
        {
          "id": 36,
          "name": "Iron Maiden",
          "hp": 250,
          "exp": 45,
          "type": "enemy"
        },
        {
          "id": 37,
          "name": "Fossil",
          "hp": 300,
          "exp": 50,
          "type": "enemy"
        },
        {
          "id": 38,
          "name": "Blue Beast",
          "hp": 350,
          "exp": 60,
          "type": "enemy"
        },
        {
          "id": 39,
          "name": "Red Beast",
          "hp": 400,
          "exp": 70,
          "type": "enemy"
        },
        {
          "id": 40,
          "name": "Gold Beast",
          "hp": 500,
          "exp": 100,
          "type": "enemy"
        }
      ],
      "locations": [
        {
          "name": "1000 AD / Present",
          "type": "era",
          "locations": [
            "Guardia Castle",
            "Leene Square",
            "Truce",
            "Melchyore"
          ]
        },
        {
          "name": "Future",
          "type": "era",
          "locations": [
            "Der Whirl",
            "Factory",
            "Sealed Chest"
          ]
        },
        {
          "name": "600 AD / Middle Ages",
          "type": "era",
          "locations": [
            "King's Table",
            "Caves",
            "Temple of Fiends"
          ]
        },
        {
          "name": "Past",
          "type": "era",
          "locations": [
            "Temple of Fiends",
            "Zenhinden"
          ]
        },
        {
          "name": "10000 BC / Prehistoric",
          "type": "era",
          "locations": [
            "Ioka",
            "Giant's Table",
            "Laruba"
          ]
        },
        {
          "name": "End of Time",
          "type": "hub",
          "locations": [
            "Epoch",
            "Time Keeper"
          ]
        },
        {
          "name": "Guardia Castle",
          "type": "dungeon",
          "era": "1000 AD"
        },
        {
          "name": "Temple of Fiends",
          "type": "dungeon",
          "era": "600 AD"
        },
        {
          "name": "Denadoro Mountains",
          "type": "dungeon",
          "era": "1000 AD"
        },
        {
          "name": "Ocean Palace",
          "type": "dungeon",
          "era": "1000 AD"
        },
        {
          "name": "Sun Keep",
          "type": "dungeon",
          "era": "1000 AD"
        },
        {
          "name": "Black Dream",
          "type": "dungeon",
          "era": "1000 AD"
        },
        {
          "name": "Ozzie's Fort",
          "type": "dungeon",
          "era": "600 AD"
        },
        {
          "name": "Zenan Bridge",
          "type": "dungeon",
          "era": "600 AD"
        },
        {
          "name": "Frog's Hideout",
          "type": "dungeon",
          "era": "600 AD"
        },
        {
          "name": "Giant's Table",
          "type": "dungeon",
          "era": "10000 BC"
        },
        {
          "name": "Laruba Ranch",
          "type": "dungeon",
          "era": "10000 BC"
        },
        {
          "name": "Mystic Mountain",
          "type": "dungeon",
          "era": "10000 BC"
        },
        {
          "name": "Factory",
          "type": "dungeon",
          "era": "Future"
        },
        {
          "name": "Death Peak",
          "type": "dungeon",
          "era": "End of Time"
        },
        {
          "name": "Chrono Trigger",
          "type": "final_dungeon",
          "era": "12000 BC"
        }
      ],
      "techs": [
        {
          "name": "Dark"
        },
        {
          "name": "Saber"
        },
        {
          "name": "Slasher"
        },
        {
          "name": "Shock"
        },
        {
          "name": "Wave"
        },
        {
          "name": "DarkScythe"
        },
        {
          "name": "Slasher"
        },
        {
          "name": "Dark"
        },
        {
          "name": "Mail"
        },
        {
          "name": "Flash"
        },
        {
          "name": "Mail"
        },
        {
          "name": "Lightning"
        },
        {
          "name": "Spincut"
        },
        {
          "name": "Lightning2"
        },
        {
          "name": "Luminaire"
        },
        {
          "name": "Aura"
        },
        {
          "name": "Provoke"
        },
        {
          "name": "Ice"
        },
        {
          "name": "Ice"
        },
        {
          "name": "Life"
        },
        {
          "name": "Flame"
        },
        {
          "name": "Toss"
        },
        {
          "name": "Hypno"
        },
        {
          "name": "Wave"
        },
        {
          "name": "Fire"
        },
        {
          "name": "Napalm"
        },
        {
          "name": "Heal"
        },
        {
          "name": "Leap"
        },
        {
          "name": "Slash"
        },
        {
          "name": "Ice"
        },
        {
          "name": "Fire"
        },
        {
          "name": "Dark"
        },
        {
          "name": "Bomb"
        },
        {
          "name": "Dark"
        },
        {
          "name": "Mist"
        },
        {
          "name": "Black"
        },
        {
          "name": "Hole"
        },
        {
          "name": "Strike"
        },
        {
          "name": "DarkE"
        },
        {
          "name": "Darkb"
        },
        {
          "name": "Darkm"
        },
        {
          "name": "Volt"
        },
        {
          "name": "Strike"
        },
        {
          "name": "Volt"
        },
        {
          "name": "Dark"
        },
        {
          "name": "Dark"
        },
        {
          "name": "Dark"
        }
      ],
      "combos": [
        {
          "name": "Delta Force",
          "chars": [
            "Crono",
            "Lucca",
            "Marle"
          ],
          "power": 150
        },
        {
          "name": "Triple Tech",
          "chars": [
            "Crono",
            "Lucca",
            "Frog"
          ],
          "power": 120
        },
        {
          "name": "Twin Bomb",
          "chars": [
            "Lucca",
            "Robo"
          ],
          "power": 80
        },
        {
          "name": "Ice Toss",
          "chars": [
            "Marle",
            "Lucca"
          ],
          "power": 60
        },
        {
          "name": "Fire Zone",
          "chars": [
            "Lucca",
            "Ayla"
          ],
          "power": 70
        },
        {
          "name": "Blaze Kick",
          "chars": [
            "Ayla",
            "Marle"
          ],
          "power": 65
        },
        {
          "name": "Drill Kick",
          "chars": [
            "Ayla",
            "Crono"
          ],
          "power": 75
        },
        {
          "name": "Dark Matter",
          "chars": [
            "Magus",
            "Lucca"
          ],
          "power": 100
        },
        {
          "name": "Giga Smash",
          "chars": [
            "Crono",
            "Ayla"
          ],
          "power": 90
        },
        {
          "name": "Bubble Snap",
          "chars": [
            "Marle",
            "Robo"
          ],
          "power": 55
        },
        {
          "name": "Final Strike",
          "chars": [
            "Crono",
            "Frog",
            "Magus"
          ],
          "power": 200
        }
      ],
      "elements": [
        {
          "name": "Fire",
          "weakness": "Water",
          "absorb": "Fire"
        },
        {
          "name": "Ice",
          "weakness": "Fire",
          "absorb": "Ice"
        },
        {
          "name": "Lightning",
          "weakness": "Water",
          "absorb": "Lightning"
        },
        {
          "name": "Water",
          "weakness": "Lightning",
          "absorb": "Water"
        }
      ],
      "status_effects": [
        {
          "name": "Poison",
          "effect": "HP damage per turn"
        },
        {
          "name": "Blind",
          "effect": "Accuracy -50%"
        },
        {
          "name": "Silence",
          "effect": "MP cannot be used"
        },
        {
          "name": "Confuse",
          "effect": "Random attacks"
        },
        {
          "name": "Stop",
          "effect": "Cannot act"
        },
        {
          "name": "Sleep",
          "effect": "Cannot act"
        },
        {
          "name": "Petrify",
          "effect": "Cannot act"
        },
        {
          "name": "Death",
          "effect": "Instant KO"
        },
        {
          "name": "Slow",
          "effect": "Speed -50%"
        },
        {
          "name": "Haste",
          "effect": "Speed +50%"
        }
      ],
      "shops": [
        {
          "name": "Guardia Shop",
          "location": "Guardia Castle"
        },
        {
          "name": "Frog's Shop",
          "location": "Frog's Hideout"
        },
        {
          "name": "Guru Shop",
          "location": "End of Time"
        },
        {
          "name": "Sewers Shop",
          "location": "Sewers"
        },
        {
          "name": "Factory Shop",
          "location": "Future Factory"
        },
        {
          "name": "Denadoro Shop",
          "location": "Denadoro Mountains"
        }
      ],
      "npcs": {
        "count": 200,
        "data": "ct_npcs.json"
      },
      "treasure": {
        "count": 100,
        "data": "ct_treasure.json"
      },
      "monster_drops": {
        "count": 50,
        "data": "ct_monster_drops.json"
      }
    },
    "Chrono Cross": {
      "game": "Chrono Cross",
      "platforms": [
        "PS1"
      ],
      "characters": [
        {
          "id": 0,
          "name": "Serge",
          "hp": 180,
          "mp": 30,
          "str": 18,
          "def": 10,
          "element": "non-elemental"
        },
        {
          "id": 1,
          "name": "Kid",
          "hp": 150,
          "mp": 45,
          "str": 12,
          "def": 8,
          "element": "shadow"
        },
        {
          "id": 2,
          "name": "Guinevere",
          "hp": 160,
          "mp": 50,
          "str": 14,
          "def": 9,
          "element": "white"
        },
        {
          "id": 3,
          "name": "Harle",
          "hp": 170,
          "mp": 35,
          "str": 16,
          "def": 12,
          "element": "dark"
        },
        {
          "id": 4,
          "name": "Lynx",
          "hp": 200,
          "mp": 20,
          "str": 22,
          "def": 15,
          "element": "shadow"
        },
        {
          "id": 5,
          "name": "Viper",
          "hp": 190,
          "mp": 15,
          "str": 25,
          "def": 12,
          "element": "earth"
        },
        {
          "id": 6,
          "name": "Frog",
          "hp": 160,
          "mp": 40,
          "str": 18,
          "def": 10,
          "element": "water"
        },
        {
          "id": 7,
          "name": "Radius",
          "hp": 200,
          "mp": 25,
          "str": 20,
          "def": 18,
          "element": "non-elemental"
        },
        {
          "id": 8,
          "name": "Marcie",
          "hp": 140,
          "mp": 55,
          "str": 10,
          "def": 7,
          "element": "wind"
        },
        {
          "id": 9,
          "name": "Doc",
          "hp": 150,
          "mp": 50,
          "str": 14,
          "def": 10,
          "element": "lightning"
        },
        {
          "id": 10,
          "name": "Harle (Astral)",
          "hp": 180,
          "mp": 40,
          "str": 18,
          "def": 14,
          "element": "dark"
        }
      ],
      "elements": [
        {
          "id": 0,
          "name": "Fire",
          "color": "red"
        },
        {
          "id": 1,
          "name": "Ice",
          "color": "cyan"
        },
        {
          "id": 2,
          "name": "Water",
          "color": "blue"
        },
        {
          "id": 3,
          "name": "Lightning",
          "color": "yellow"
        },
        {
          "id": 4,
          "name": "Earth",
          "color": "brown"
        },
        {
          "id": 5,
          "name": "Wind",
          "color": "green"
        },
        {
          "id": 6,
          "name": "Dark",
          "color": "purple"
        },
        {
          "id": 7,
          "name": "Holy",
          "color": "white"
        }
      ],
      "locations": [
        {
          "id": 0,
          "name": "Home",
          "type": "town",
          "region": "Home"
        },
        {
          "id": 1,
          "name": "Arni Village",
          "type": "town",
          "region": "Coast"
        },
        {
          "id": 2,
          "name": "Lucca's Theater",
          "type": "building",
          "region": "Coast"
        },
        {
          "id": 3,
          "name": "Marbule",
          "type": "town",
          "region": "West"
        },
        {
          "id": 4,
          "name": "Guldove",
          "type": "town",
          "region": "Islands"
        },
        {
          "id": 5,
          "name": "Termina",
          "type": "town",
          "region": "Central"
        },
        {
          "id": 6,
          "name": "Viper Manor",
          "type": "dungeon",
          "region": "West"
        },
        {
          "id": 7,
          "name": "Dead Sea",
          "type": "dungeon",
          "region": "Islands"
        },
        {
          "id": 8,
          "name": "Fort Dragonia",
          "type": "dungeon",
          "region": "Islands"
        },
        {
          "id": 9,
          "name": "Temporal Vortex",
          "type": "dungeon",
          "region": "Other"
        }
      ]
    },
    "Radical Dreamers": {
      "game": "Radical Dreamers",
      "platforms": [
        "SNES",
        "Satellaview"
      ],
      "characters": [
        {
          "id": 0,
          "name": "Serge",
          "hp": 100,
          "mp": 20,
          "str": 10,
          "def": 5
        },
        {
          "id": 1,
          "name": "Kid",
          "hp": 80,
          "mp": 30,
          "str": 8,
          "def": 4
        },
        {
          "id": 2,
          "name": "Gil",
          "hp": 90,
          "mp": 15,
          "str": 12,
          "def": 6
        },
        {
          "id": 3,
          "name": "Mana",
          "hp": 70,
          "mp": 40,
          "str": 6,
          "def": 3
        }
      ],
      "locations": [
        {
          "id": 0,
          "name": "The Dream Sanctuary",
          "type": "hub"
        },
        {
          "id": 1,
          "name": "Karsh's Castle",
          "type": "dungeon"
        },
        {
          "id": 2,
          "name": "Marbule Ruins",
          "type": "dungeon"
        },
        {
          "id": 3,
          "name": "Island of the Dead",
          "type": "dungeon"
        }
      ]
    }
  }
}